swarmauri_measurement_tokencountestimator/TokenCountEstimatorMeasurement.py
swarmauri_measurement_tokencountestimator/__init__.py
swarmauri_measurement_tokencountestimator-0.7.5.dist-info/LICENSE
swarmauri_measurement_tokencountestimator-0.7.5.dist-info/METADATA
swarmauri_measurement_tokencountestimator-0.7.5.dist-info/WHEEL
swarmauri_measurement_tokencountestimator-0.7.5.dist-info/entry_points.txt
swarmauri_measurement_tokencountestimator-0.7.5.dist-info/RECORD
